{"point": "KT", "name": "口之津", "lat": 32.6, "lon": 130.2, "data": {"2021/04/01": {"tide": [327, 274, 204, 135, 84, 64, 81, 126, 186, 250, 304, 328, 307, 249, 173, 98, 40, 13, 23, 63, 122, 191, 259, 309], "high_time": ["11:03", "23:51"], "high_tide": [328, 324], "low_time": ["05:01", "17:14"], "low_tide": [64, 12], "sunrise": "21:07", "sunset": "09:39", "tidetype": "中潮", "date": "04/01"}, "2021/04/02": {"tide": [323, 299, 249, 190, 136, 103, 99, 124, 168, 220, 270, 303, 305, 270, 210, 141, 80, 40, 28, 47, 89, 144, 204, 257], "high_time": ["11:33", "--:--"], "high_tide": [309, "--"], "low_time": ["05:37", "17:52"], "low_tide": [97, 28], "sunrise": "21:06", "sunset": "09:39", "tidetype": "中潮", "date": "04/02"}, "2021/04/03": {"tide": [291, 295, 271, 230, 186, 149, 131, 136, 161, 198, 238, 270, 285, 272, 235, 182, 128, 83, 57, 54, 74, 111, 156, 203], "high_time": ["00:37", "12:04"], "high_tide": [297, 285], "low_time": ["06:17", "18:36"], "low_tide": [130, 52], "sunrise": "21:04", "sunset": "09:40", "tidetype": "中潮", "date": "04/03"}, "2021/04/04": {"tide": [242, 265, 267, 251, 224, 195, 172, 161, 167, 185, 210, 235, 253, 256, 243, 213, 175, 135, 103, 84, 81, 95, 121, 154], "high_time": ["01:36", "12:43"], "high_tide": [269, 257], "low_time": ["07:09", "19:39"], "low_tide": [161, 80], "sunrise": "21:03", "sunset": "09:41", "tidetype": "中潮", "date": "04/04"}, "2021/04/05": {"tide": [189, 219, 241, 250, 246, 232, 213, 196, 184, 182, 188, 200, 214, 226, 230, 226, 211, 187, 159, 131, 111, 100, 102, 116], "high_time": ["03:11", "14:02"], "high_tide": [250, 230], "low_time": ["08:46", "21:20"], "low_tide": [182, 100], "sunrise": "21:02", "sunset": "09:42", "tidetype": "小潮", "date": "04/05"}, "2021/04/06": {"tide": [140, 169, 199, 227, 247, 255, 250, 234, 213, 193, 178, 172, 175, 186, 201, 216, 226, 226, 213, 188, 158, 128, 106, 96], "high_time": ["05:06", "16:30"], "high_tide": [255, 227], "low_time": ["11:07", "23:08"], "low_tide": [172, 96], "sunrise": "21:01", "sunset": "09:42", "tidetype": "小潮", "date": "04/06"}, "2021/04/07": {"tide": [102, 121, 152, 190, 228, 258, 273, 269, 248, 217, 183, 156, 143, 145, 162, 188, 217, 242, 252, 241, 212, 172, 130, 97], "high_time": ["06:17", "18:01"], "high_tide": [274, 252], "low_time": ["12:21", "--:--"], "low_tide": [142, "--"], "sunrise": "20:59", "sunset": "09:43", "tidetype": "小潮", "date": "04/07"}, "2021/04/08": {"tide": [80, 85, 108, 147, 194, 242, 278, 293, 282, 248, 203, 158, 124, 111, 121, 150, 190, 233, 267, 279, 264, 224, 171, 119], "high_time": ["07:04", "18:57"], "high_tide": [293, 279], "low_time": ["00:18", "13:03"], "low_tide": [79, 111], "sunrise": "20:58", "sunset": "09:44", "tidetype": "長潮", "date": "04/08"}, "2021/04/09": {"tide": [80, 64, 74, 107, 156, 212, 265, 300, 306, 280, 232, 175, 123, 91, 87, 110, 153, 205, 257, 294, 300, 272, 219, 157], "high_time": ["07:40", "19:41"], "high_tide": [307, 302], "low_time": ["01:06", "13:38"], "low_tide": [64, 85], "sunrise": "20:57", "sunset": "09:44", "tidetype": "若潮", "date": "04/09"}, "2021/04/10": {"tide": [100, 63, 55, 77, 121, 178, 239, 291, 316, 305, 261, 200, 137, 87, 65, 76, 114, 168, 230, 285, 315, 307, 265, 201], "high_time": ["08:12", "20:19"], "high_tide": [317, 317], "low_time": ["01:45", "14:10"], "low_tide": [54, 64], "sunrise": "20:55", "sunset": "09:45", "tidetype": "中潮", "date": "04/10"}, "2021/04/11": {"tide": [134, 80, 52, 58, 93, 147, 209, 270, 312, 319, 287, 228, 159, 97, 57, 52, 79, 130, 194, 259, 309, 325, 301, 245], "high_time": ["08:40", "20:54"], "high_tide": [321, 326], "low_time": ["02:19", "14:39"], "low_tide": [51, 49], "sunrise": "20:54", "sunset": "09:46", "tidetype": "中潮", "date": "04/11"}, "2021/04/12": {"tide": [175, 110, 66, 54, 75, 122, 181, 245, 298, 322, 306, 254, 185, 115, 62, 39, 52, 95, 156, 224, 287, 325, 322, 281], "high_time": ["09:06", "21:27"], "high_tide": [323, 329], "low_time": ["02:50", "15:07"], "low_tide": [53, 39], "sunrise": "20:53", "sunset": "09:47", "tidetype": "大潮", "date": "04/12"}, "2021/04/13": {"tide": [217, 148, 91, 62, 68, 104, 158, 220, 279, 317, 317, 277, 211, 139, 76, 39, 36, 67, 121, 187, 256, 309, 328, 306], "high_time": ["09:30", "21:58"], "high_tide": [322, 328], "low_time": ["03:20", "15:34"], "low_tide": [60, 33], "sunrise": "20:52", "sunset": "09:47", "tidetype": "大潮", "date": "04/13"}, "2021/04/14": {"tide": [253, 187, 124, 82, 72, 94, 140, 198, 258, 304, 319, 294, 236, 165, 97, 49, 31, 48, 92, 153, 221, 282, 319, 317], "high_time": ["09:53", "22:27"], "high_tide": [319, 323], "low_time": ["03:49", "16:00"], "low_tide": [71, 31], "sunrise": "20:51", "sunset": "09:48", "tidetype": "大潮", "date": "04/14"}, "2021/04/15": {"tide": [280, 222, 160, 110, 86, 93, 128, 179, 236, 286, 313, 303, 257, 191, 122, 67, 37, 40, 73, 125, 188, 250, 297, 314], "high_time": ["10:14", "22:57"], "high_tide": [314, 314], "low_time": ["04:16", "16:25"], "low_tide": [85, 35], "sunrise": "20:49", "sunset": "09:49", "tidetype": "中潮", "date": "04/15"}, "2021/04/16": {"tide": [294, 249, 194, 143, 109, 103, 125, 166, 217, 265, 299, 302, 271, 214, 149, 92, 53, 43, 63, 105, 160, 218, 269, 298], "high_time": ["10:36", "23:26"], "high_tide": [305, 301], "low_time": ["04:42", "16:49"], "low_tide": [102, 43], "sunrise": "20:48", "sunset": "09:49", "tidetype": "中潮", "date": "04/16"}, "2021/04/17": {"tide": [296, 266, 221, 174, 137, 121, 129, 159, 201, 244, 279, 292, 276, 233, 176, 120, 77, 57, 63, 93, 137, 188, 236, 272], "high_time": ["10:58", "23:58"], "high_tide": [292, 284], "low_time": ["05:09", "17:16"], "low_tide": [120, 56], "sunrise": "20:47", "sunset": "09:50", "tidetype": "中潮", "date": "04/17"}, "2021/04/18": {"tide": [284, 271, 240, 202, 167, 144, 142, 159, 189, 225, 256, 275, 272, 244, 200, 150, 107, 80, 73, 88, 119, 160, 203, 240], "high_time": ["11:22", "--:--"], "high_tide": [277, "--"], "low_time": ["05:38", "17:48"], "low_tide": [140, 72], "sunrise": "20:46", "sunset": "09:51", "tidetype": "中潮", "date": "04/18"}, "2021/04/19": {"tide": [262, 265, 250, 224, 196, 172, 161, 165, 182, 207, 232, 252, 258, 246, 218, 181, 143, 112, 94, 93, 108, 135, 169, 203], "high_time": ["00:38", "11:52"], "high_tide": [267, 258], "low_time": ["06:15", "18:34"], "low_tide": [160, 91], "sunrise": "20:45", "sunset": "09:52", "tidetype": "小潮", "date": "04/19"}, "2021/04/20": {"tide": [231, 247, 250, 240, 222, 203, 186, 178, 180, 191, 207, 223, 235, 237, 228, 208, 182, 154, 129, 112, 108, 116, 134, 161], "high_time": ["01:40", "12:42"], "high_tide": [250, 237], "low_time": ["07:18", "19:52"], "low_tide": [178, 108], "sunrise": "20:44", "sunset": "09:52", "tidetype": "小潮", "date": "04/20"}, "2021/04/21": {"tide": [190, 216, 235, 245, 244, 234, 218, 201, 188, 181, 183, 190, 202, 214, 222, 224, 217, 201, 177, 150, 126, 111, 108, 119], "high_time": ["03:25", "14:41"], "high_tide": [246, 224], "low_time": ["09:21", "21:42"], "low_tide": [181, 108], "sunrise": "20:42", "sunset": "09:53", "tidetype": "小潮", "date": "04/21"}, "2021/04/22": {"tide": [142, 173, 205, 233, 253, 261, 254, 235, 209, 184, 166, 158, 163, 178, 198, 219, 235, 240, 230, 204, 168, 131, 102, 89], "high_time": ["05:02", "16:52"], "high_tide": [261, 241], "low_time": ["11:07", "23:09"], "low_tide": [158, 89], "sunrise": "20:41", "sunset": "09:54", "tidetype": "長潮", "date": "04/22"}, "2021/04/23": {"tide": [96, 122, 160, 202, 242, 272, 284, 274, 245, 204, 165, 135, 123, 132, 157, 192, 228, 259, 273, 263, 228, 177, 126, 85], "high_time": ["06:03", "18:07"], "high_tide": [284, 273], "low_time": ["12:05", "--:--"], "low_tide": [123, "--"], "sunrise": "20:40", "sunset": "09:54", "tidetype": "若潮", "date": "04/23"}, "2021/04/24": {"tide": [66, 75, 108, 156, 210, 261, 297, 308, 287, 241, 185, 133, 97, 87, 105, 144, 194, 246, 288, 307, 291, 243, 179, 115], "high_time": ["06:50", "19:04"], "high_tide": [308, 307], "low_time": ["00:12", "12:50"], "low_tide": [66, 86], "sunrise": "20:39", "sunset": "09:55", "tidetype": "中潮", "date": "04/24"}, "2021/04/25": {"tide": [67, 48, 62, 105, 163, 226, 284, 322, 324, 287, 224, 154, 94, 58, 56, 87, 140, 203, 267, 317, 335, 309, 250, 175], "high_time": ["07:33", "19:55"], "high_tide": [328, 335], "low_time": ["01:04", "13:33"], "low_tide": [48, 52], "sunrise": "20:38", "sunset": "09:56", "tidetype": "中潮", "date": "04/25"}, "2021/04/26": {"tide": [104, 55, 40, 63, 114, 179, 248, 309, 340, 327, 272, 196, 117, 55, 25, 35, 79, 143, 217, 289, 342, 352, 316, 248], "high_time": ["08:13", "20:43"], "high_tide": [341, 354], "low_time": ["01:53", "14:15"], "low_tide": [40, 24], "sunrise": "20:37", "sunset": "09:57", "tidetype": "大潮", "date": "04/26"}, "2021/04/27": {"tide": [168, 97, 52, 45, 77, 133, 202, 273, 329, 347, 315, 245, 160, 80, 23, 4, 27, 81, 152, 233, 309, 357, 357, 312], "high_time": ["08:52", "21:30"], "high_tide": [347, 363], "low_time": ["02:39", "14:56"], "low_tide": [43, 4], "sunrise": "20:36", "sunset": "09:57", "tidetype": "大潮", "date": "04/27"}, "2021/04/28": {"tide": [239, 161, 95, 59, 62, 101, 160, 229, 296, 340, 339, 290, 210, 124, 49, 3, -3, 31, 91, 167, 250, 323, 360, 349], "high_time": ["09:29", "22:16"], "high_tide": [346, 362], "low_time": ["03:24", "15:37"], "low_tide": [55, -6], "sunrise": "20:35", "sunset": "09:58", "tidetype": "大潮", "date": "04/28"}, "2021/04/29": {"tide": [298, 227, 155, 99, 75, 89, 132, 191, 256, 313, 339, 318, 256, 174, 92, 28, -3, 5, 47, 110, 187, 265, 327, 350], "high_time": ["10:04", "23:01"], "high_tide": [339, 350], "low_time": ["04:07", "16:17"], "low_tide": [75, -5], "sunrise": "20:34", "sunset": "09:59", "tidetype": "大潮", "date": "04/29"}, "2021/04/30": {"tide": [329, 278, 213, 152, 110, 99, 121, 165, 220, 276, 317, 323, 287, 220, 143, 72, 23, 7, 25, 71, 134, 205, 273, 319], "high_time": ["10:38", "23:46"], "high_tide": [325, 330], "low_time": ["04:48", "16:57"], "low_tide": [99, 7], "sunrise": "20:33", "sunset": "09:59", "tidetype": "中潮", "date": "04/30"}}}