{"point": "KB", "name": "神戸", "lat": 34.68333333, "lon": 135.1833333, "data": {"2020/02/01": {"tide": [82, 74, 68, 63, 59, 58, 63, 70, 78, 87, 97, 104, 104, 99, 94, 88, 80, 70, 63, 60, 59, 61, 67, 74], "high_time": ["11:32", "--:--"], "high_tide": [105, "--"], "low_time": ["04:42", "19:53"], "low_tide": [58, 59], "sunrise": "21:57", "sunset": "08:27", "tidetype": "小潮", "date": "02/01"}, "2020/02/02": {"tide": [77, 76, 74, 73, 73, 72, 74, 79, 85, 90, 95, 100, 102, 99, 93, 88, 81, 73, 63, 55, 51, 49, 51, 58], "high_time": ["00:10", "11:56"], "high_tide": [77, 102], "low_time": ["04:54", "21:01"], "low_tide": [72, 49], "sunrise": "21:57", "sunset": "08:28", "tidetype": "小潮", "date": "02/02"}, "2020/02/03": {"tide": [66, 73, 76, 79, 82, 85, 86, 88, 92, 95, 97, 98, 100, 99, 94, 88, 82, 75, 65, 54, 45, 40, 38, 41], "high_time": ["12:17", "--:--"], "high_tide": [100, "--"], "low_time": ["21:56", "--:--"], "low_tide": [38, "--"], "sunrise": "21:56", "sunset": "08:29", "tidetype": "小潮", "date": "02/03"}, "2020/02/04": {"tide": [50, 62, 72, 81, 88, 95, 98, 98, 99, 100, 101, 100, 99, 99, 97, 92, 85, 78, 68, 56, 43, 34, 28, 27], "high_time": ["09:53", "--:--"], "high_tide": [101, "--"], "low_time": ["22:41", "--:--"], "low_tide": [26, "--"], "sunrise": "21:55", "sunset": "08:30", "tidetype": "長潮", "date": "02/04"}, "2020/02/05": {"tide": [32, 45, 61, 77, 91, 101, 107, 108, 107, 104, 103, 101, 100, 100, 100, 98, 93, 86, 75, 62, 47, 32, 20, 14], "high_time": ["06:47", "--:--"], "high_tide": [108, "--"], "low_time": ["23:19", "--:--"], "low_tide": [13, "--"], "sunrise": "21:54", "sunset": "08:31", "tidetype": "若潮", "date": "02/05"}, "2020/02/06": {"tide": [15, 25, 43, 66, 88, 105, 115, 117, 115, 109, 103, 99, 99, 100, 101, 103, 103, 99, 88, 73, 55, 36, 18, 4], "high_time": ["06:57", "15:40"], "high_tide": [117, 103], "low_time": ["11:44", "23:53"], "low_tide": [99, 0], "sunrise": "21:54", "sunset": "08:32", "tidetype": "中潮", "date": "02/06"}, "2020/02/07": {"tide": [0, 6, 22, 46, 76, 103, 120, 125, 123, 115, 105, 96, 92, 95, 100, 104, 109, 113, 108, 92, 70, 48, 25, 2], "high_time": ["07:01", "17:02"], "high_tide": [125, 113], "low_time": ["11:57", "--:--"], "low_tide": [92, "--"], "sunrise": "21:53", "sunset": "08:33", "tidetype": "中潮", "date": "02/07"}, "2020/02/08": {"tide": [-12, -11, 1, 23, 54, 91, 121, 133, 131, 122, 110, 95, 84, 85, 93, 101, 109, 120, 126, 116, 93, 67, 41, 13], "high_time": ["07:14", "17:58"], "high_tide": [133, 126], "low_time": ["00:28", "12:28"], "low_tide": [-13, 83], "sunrise": "21:52", "sunset": "08:34", "tidetype": "大潮", "date": "02/08"}, "2020/02/09": {"tide": [-12, -23, -16, 3, 30, 68, 109, 136, 139, 129, 116, 100, 81, 72, 79, 91, 102, 115, 131, 136, 121, 92, 62, 33], "high_time": ["07:39", "18:48"], "high_tide": [140, 137], "low_time": ["01:04", "13:04"], "low_tide": [-23, 72], "sunrise": "21:51", "sunset": "08:35", "tidetype": "大潮", "date": "02/09"}, "2020/02/10": {"tide": [2, -22, -27, -13, 10, 42, 86, 126, 144, 138, 123, 106, 86, 68, 64, 75, 90, 103, 121, 139, 141, 119, 88, 58], "high_time": ["08:09", "19:34"], "high_tide": [144, 143], "low_time": ["01:41", "13:43"], "low_tide": [-28, 63], "sunrise": "21:50", "sunset": "08:36", "tidetype": "大潮", "date": "02/10"}, "2020/02/11": {"tide": [28, -4, -23, -19, -1, 24, 59, 103, 137, 143, 130, 113, 95, 73, 57, 59, 72, 86, 102, 123, 141, 137, 112, 83], "high_time": ["08:43", "20:20"], "high_tide": [144, 142], "low_time": ["02:20", "14:25"], "low_tide": [-24, 56], "sunrise": "21:49", "sunset": "08:37", "tidetype": "大潮", "date": "02/11"}, "2020/02/12": {"tide": [56, 26, -1, -11, -2, 17, 42, 77, 116, 138, 134, 118, 102, 83, 63, 52, 56, 68, 81, 98, 120, 134, 125, 102], "high_time": ["09:19", "21:08"], "high_tide": [139, 134], "low_time": ["02:59", "15:11"], "low_tide": [-11, 51], "sunrise": "21:48", "sunset": "08:38", "tidetype": "中潮", "date": "02/12"}, "2020/02/13": {"tide": [79, 56, 32, 13, 10, 21, 39, 62, 93, 122, 132, 122, 106, 91, 74, 57, 49, 53, 62, 73, 90, 110, 119, 110], "high_time": ["09:56", "21:59"], "high_tide": [132, 119], "low_time": ["03:39", "16:05"], "low_tide": [9, 49], "sunrise": "21:47", "sunset": "08:39", "tidetype": "中潮", "date": "02/13"}, "2020/02/14": {"tide": [93, 77, 61, 45, 34, 37, 47, 61, 80, 103, 120, 120, 109, 95, 82, 68, 54, 47, 49, 55, 64, 79, 95, 101], "high_time": ["10:32", "23:00"], "high_tide": [122, 101], "low_time": ["04:19", "17:12"], "low_tide": [34, 47], "sunrise": "21:46", "sunset": "08:40", "tidetype": "中潮", "date": "02/14"}, "2020/02/15": {"tide": [96, 87, 80, 72, 63, 60, 64, 72, 81, 93, 106, 113, 109, 98, 87, 76, 63, 52, 45, 44, 46, 53, 65, 78], "high_time": ["11:06", "--:--"], "high_tide": [113, "--"], "low_time": ["04:58", "18:48"], "low_tide": [60, 44], "sunrise": "21:45", "sunset": "08:41", "tidetype": "中潮", "date": "02/15"}, "2020/02/16": {"tide": [85, 86, 86, 86, 85, 83, 84, 87, 91, 96, 100, 105, 105, 99, 89, 80, 71, 61, 49, 41, 37, 37, 42, 52], "high_time": ["01:53", "11:32"], "high_tide": [87, 105], "low_time": ["05:30", "20:28"], "low_tide": [83, 37], "sunrise": "21:44", "sunset": "08:42", "tidetype": "小潮", "date": "02/16"}, "2020/02/17": {"tide": [64, 75, 83, 89, 95, 99, 101, 102, 103, 104, 103, 102, 101, 98, 92, 85, 77, 68, 58, 46, 36, 30, 28, 32], "high_time": ["09:09", "--:--"], "high_tide": [104, "--"], "low_time": ["21:49", "--:--"], "low_tide": [28, "--"], "sunrise": "21:43", "sunset": "08:43", "tidetype": "小潮", "date": "02/17"}, "2020/02/18": {"tide": [42, 56, 71, 85, 96, 105, 111, 113, 112, 110, 108, 105, 101, 97, 94, 90, 84, 76, 66, 55, 42, 30, 22, 20], "high_time": ["07:08", "--:--"], "high_tide": [113, "--"], "low_time": ["22:47", "--:--"], "low_tide": [20, "--"], "sunrise": "21:42", "sunset": "08:44", "tidetype": "小潮", "date": "02/18"}, "2020/02/19": {"tide": [25, 36, 54, 75, 93, 106, 114, 118, 118, 114, 109, 106, 102, 98, 95, 94, 93, 86, 76, 65, 52, 37, 22, 14], "high_time": ["07:29", "--:--"], "high_tide": [119, "--"], "low_time": ["23:27", "--:--"], "low_tide": [13, "--"], "sunrise": "21:41", "sunset": "08:45", "tidetype": "長潮", "date": "02/19"}, "2020/02/20": {"tide": [14, 21, 36, 59, 85, 105, 115, 119, 120, 115, 108, 101, 99, 98, 96, 96, 99, 99, 90, 76, 63, 48, 29, 13], "high_time": ["07:41", "16:31"], "high_tide": [120, 100], "low_time": ["14:32", "--:--"], "low_tide": [95, "--"], "sunrise": "21:40", "sunset": "08:46", "tidetype": "若潮", "date": "02/20"}, "2020/02/21": {"tide": [7, 11, 22, 42, 70, 99, 117, 121, 119, 115, 106, 95, 91, 93, 95, 96, 101, 108, 106, 93, 76, 60, 41, 19], "high_time": ["07:02", "17:24"], "high_tide": [121, 108], "low_time": ["00:01", "12:01"], "low_tide": [7, 91], "sunrise": "21:39", "sunset": "08:47", "tidetype": "中潮", "date": "02/21"}, "2020/02/22": {"tide": [5, 4, 13, 28, 54, 87, 115, 125, 121, 115, 105, 91, 81, 81, 88, 93, 99, 109, 117, 111, 92, 73, 54, 32], "high_time": ["07:05", "18:07"], "high_tide": [125, 117], "low_time": ["00:32", "12:26"], "low_tide": [3, 80], "sunrise": "21:37", "sunset": "08:48", "tidetype": "中潮", "date": "02/22"}, "2020/02/23": {"tide": [10, 1, 6, 20, 40, 71, 106, 126, 126, 117, 106, 91, 75, 69, 76, 86, 94, 105, 119, 124, 110, 88, 67, 46], "high_time": ["07:28", "18:46"], "high_tide": [128, 124], "low_time": ["01:03", "12:56"], "low_tide": [1, 69], "sunrise": "21:36", "sunset": "08:49", "tidetype": "大潮", "date": "02/23"}, "2020/02/24": {"tide": [22, 4, 3, 14, 31, 56, 91, 121, 130, 121, 108, 94, 76, 62, 63, 74, 86, 97, 113, 127, 124, 104, 81, 60], "high_time": ["07:54", "19:22"], "high_tide": [130, 128], "low_time": ["01:33", "13:28"], "low_tide": [2, 61], "sunrise": "21:35", "sunset": "08:50", "tidetype": "大潮", "date": "02/24"}, "2020/02/25": {"tide": [37, 16, 6, 13, 27, 47, 76, 109, 128, 126, 112, 97, 80, 63, 55, 61, 74, 87, 102, 120, 127, 117, 94, 73], "high_time": ["08:22", "19:56"], "high_tide": [130, 128], "low_time": ["02:02", "14:01"], "low_tide": [6, 55], "sunrise": "21:34", "sunset": "08:50", "tidetype": "大潮", "date": "02/25"}, "2020/02/26": {"tide": [52, 31, 16, 16, 28, 44, 66, 95, 120, 126, 116, 101, 85, 68, 54, 52, 62, 74, 88, 106, 121, 121, 105, 84], "high_time": ["08:48", "20:31"], "high_tide": [127, 124], "low_time": ["02:29", "14:37"], "low_tide": [14, 51], "sunrise": "21:33", "sunset": "08:51", "tidetype": "大潮", "date": "02/26"}, "2020/02/27": {"tide": [65, 47, 31, 25, 32, 46, 62, 84, 109, 122, 118, 104, 90, 74, 59, 49, 52, 62, 73, 89, 107, 116, 110, 93], "high_time": ["09:14", "21:07"], "high_tide": [123, 117], "low_time": ["02:54", "15:15"], "low_tide": [25, 49], "sunrise": "21:31", "sunset": "08:52", "tidetype": "中潮", "date": "02/27"}, "2020/02/28": {"tide": [77, 61, 47, 38, 40, 51, 64, 79, 99, 114, 116, 106, 93, 80, 66, 53, 48, 52, 60, 72, 87, 103, 107, 99], "high_time": ["09:38", "21:48"], "high_tide": [117, 107], "low_time": ["03:18", "15:58"], "low_tide": [38, 48], "sunrise": "21:30", "sunset": "08:53", "tidetype": "中潮", "date": "02/28"}, "2020/02/29": {"tide": [85, 73, 63, 54, 52, 58, 69, 80, 93, 106, 112, 106, 94, 83, 71, 59, 49, 47, 50, 58, 69, 83, 95, 97], "high_time": ["10:01", "22:38"], "high_tide": [112, 97], "low_time": ["03:44", "16:50"], "low_tide": [52, 47], "sunrise": "21:29", "sunset": "08:54", "tidetype": "中潮", "date": "02/29"}}}