{"point": "X2", "name": "平戸瀬戸", "lat": 33.36666667, "lon": 129.5833333, "data": {"2020/02/01": {"tide": [184, 186, 174, 150, 121, 94, 77, 76, 90, 116, 146, 173, 192, 197, 190, 172, 146, 119, 96, 83, 83, 96, 116, 139], "high_time": ["00:37", "12:56"], "high_tide": [187, 198], "low_time": ["06:35", "19:28"], "low_tide": [74, 81], "sunrise": "22:17", "sunset": "08:52", "tidetype": "小潮", "date": "02/01"}, "2020/02/02": {"tide": [159, 170, 171, 161, 144, 123, 105, 96, 99, 113, 133, 156, 174, 185, 187, 178, 162, 140, 116, 96, 85, 85, 94, 110], "high_time": ["01:34", "13:39"], "high_tide": [172, 187], "low_time": ["07:16", "20:32"], "low_tide": [96, 84], "sunrise": "22:17", "sunset": "08:53", "tidetype": "小潮", "date": "02/02"}, "2020/02/03": {"tide": [128, 145, 157, 162, 158, 149, 135, 123, 116, 118, 127, 140, 155, 168, 177, 179, 173, 160, 141, 118, 97, 83, 79, 83], "high_time": ["03:04", "14:46"], "high_tide": [162, 179], "low_time": ["08:17", "21:59"], "low_tide": [116, 79], "sunrise": "22:16", "sunset": "08:54", "tidetype": "小潮", "date": "02/03"}, "2020/02/04": {"tide": [96, 114, 134, 151, 162, 166, 162, 152, 141, 132, 128, 130, 137, 148, 161, 172, 178, 177, 166, 146, 120, 94, 74, 64], "high_time": ["05:00", "16:20"], "high_tide": [166, 179], "low_time": ["10:09", "23:22"], "low_tide": [128, 63], "sunrise": "22:15", "sunset": "08:55", "tidetype": "長潮", "date": "02/04"}, "2020/02/05": {"tide": [66, 79, 101, 128, 153, 172, 182, 181, 171, 155, 139, 127, 123, 128, 140, 157, 175, 187, 188, 176, 151, 118, 84, 57], "high_time": ["06:25", "17:38"], "high_tide": [183, 189], "low_time": ["12:01", "--:--"], "low_tide": [123, "--"], "sunrise": "22:15", "sunset": "08:56", "tidetype": "若潮", "date": "02/05"}, "2020/02/06": {"tide": [43, 45, 62, 93, 129, 164, 191, 204, 202, 185, 161, 135, 117, 109, 116, 134, 160, 186, 203, 204, 188, 155, 111, 67], "high_time": ["07:20", "18:36"], "high_tide": [205, 206], "low_time": ["00:23", "13:03"], "low_tide": [41, 109], "sunrise": "22:14", "sunset": "08:57", "tidetype": "中潮", "date": "02/06"}, "2020/02/07": {"tide": [33, 18, 24, 50, 92, 140, 184, 215, 226, 218, 192, 156, 122, 99, 93, 106, 134, 171, 204, 223, 222, 198, 154, 98], "high_time": ["08:05", "19:26"], "high_tide": [226, 225], "low_time": ["01:14", "13:49"], "low_tide": [17, 93], "sunrise": "22:13", "sunset": "08:58", "tidetype": "中潮", "date": "02/07"}, "2020/02/08": {"tide": [44, 7, -6, 8, 46, 100, 159, 208, 239, 245, 227, 188, 141, 101, 78, 78, 100, 141, 188, 226, 244, 236, 202, 146], "high_time": ["08:46", "20:13"], "high_tide": [246, 244], "low_time": ["01:59", "14:30"], "low_tide": [-6, 75], "sunrise": "22:12", "sunset": "08:59", "tidetype": "大潮", "date": "02/08"}, "2020/02/09": {"tide": [79, 20, -17, -23, 1, 52, 118, 184, 233, 258, 256, 225, 174, 118, 76, 59, 68, 102, 154, 207, 246, 259, 244, 200], "high_time": ["09:24", "20:59"], "high_tide": [261, 259], "low_time": ["02:43", "15:10"], "low_tide": [-24, 58], "sunrise": "22:11", "sunset": "09:00", "tidetype": "大潮", "date": "02/09"}, "2020/02/10": {"tide": [133, 59, -1, -32, -29, 7, 69, 143, 209, 253, 270, 255, 211, 150, 92, 54, 45, 65, 110, 170, 225, 260, 266, 243], "high_time": ["10:02", "21:44"], "high_tide": [270, 268], "low_time": ["03:25", "15:49"], "low_tide": [-35, 44], "sunrise": "22:10", "sunset": "09:01", "tidetype": "大潮", "date": "02/10"}, "2020/02/11": {"tide": [189, 116, 41, -13, -35, -21, 26, 96, 170, 230, 265, 269, 242, 188, 123, 68, 38, 39, 69, 122, 184, 235, 263, 263], "high_time": ["10:39", "22:29"], "high_tide": [271, 267], "low_time": ["04:06", "16:28"], "low_tide": [-35, 34], "sunrise": "22:10", "sunset": "09:02", "tidetype": "大潮", "date": "02/11"}, "2020/02/12": {"tide": [232, 173, 99, 31, -12, -22, 2, 56, 127, 194, 243, 265, 257, 219, 159, 97, 50, 31, 41, 79, 134, 192, 235, 255], "high_time": ["11:14", "23:15"], "high_tide": [266, 256], "low_time": ["04:47", "17:08"], "low_tide": [-23, 30], "sunrise": "22:09", "sunset": "09:03", "tidetype": "中潮", "date": "02/12"}, "2020/02/13": {"tide": [248, 214, 155, 89, 33, 3, 5, 37, 92, 155, 210, 245, 253, 234, 190, 132, 78, 42, 33, 51, 91, 142, 191, 224], "high_time": ["11:48", "--:--"], "high_tide": [254, "--"], "low_time": ["05:27", "17:49"], "low_tide": [0, 33], "sunrise": "22:08", "sunset": "09:03", "tidetype": "中潮", "date": "02/13"}, "2020/02/14": {"tide": [237, 227, 193, 142, 88, 47, 30, 41, 75, 125, 176, 216, 235, 232, 207, 163, 113, 69, 44, 43, 63, 99, 142, 180], "high_time": ["00:03", "12:22"], "high_tide": [237, 237], "low_time": ["06:06", "18:34"], "low_tide": [30, 41], "sunrise": "22:07", "sunset": "09:04", "tidetype": "中潮", "date": "02/14"}, "2020/02/15": {"tide": [205, 213, 202, 175, 136, 97, 71, 65, 79, 110, 149, 185, 210, 218, 208, 183, 145, 104, 71, 54, 55, 73, 101, 133], "high_time": ["00:57", "12:58"], "high_tide": [213, 218], "low_time": ["06:48", "19:25"], "low_tide": [65, 52], "sunrise": "22:06", "sunset": "09:05", "tidetype": "中潮", "date": "02/15"}, "2020/02/16": {"tide": [161, 180, 188, 183, 165, 140, 116, 101, 99, 112, 133, 159, 182, 196, 198, 188, 167, 137, 105, 80, 66, 65, 76, 95], "high_time": ["02:06", "13:42"], "high_tide": [188, 199], "low_time": ["07:36", "20:32"], "low_tide": [98, 64], "sunrise": "22:05", "sunset": "09:06", "tidetype": "小潮", "date": "02/16"}, "2020/02/17": {"tide": [117, 140, 158, 169, 173, 167, 154, 139, 129, 126, 131, 142, 156, 170, 180, 183, 177, 162, 140, 114, 91, 75, 68, 71], "high_time": ["03:52", "14:51"], "high_tide": [173, 183], "low_time": ["08:51", "22:12"], "low_tide": [126, 68], "sunrise": "22:04", "sunset": "09:07", "tidetype": "小潮", "date": "02/17"}, "2020/02/18": {"tide": [82, 99, 121, 142, 162, 174, 178, 172, 161, 148, 139, 135, 137, 145, 157, 168, 176, 177, 168, 150, 125, 98, 76, 62], "high_time": ["05:52", "16:36"], "high_tide": [178, 178], "low_time": ["11:09", "23:51"], "low_tide": [135, 58], "sunrise": "22:03", "sunset": "09:08", "tidetype": "小潮", "date": "02/18"}, "2020/02/19": {"tide": [58, 66, 84, 109, 139, 166, 186, 194, 190, 175, 155, 136, 125, 123, 131, 147, 166, 181, 187, 181, 161, 132, 98, 68], "high_time": ["07:07", "18:01"], "high_tide": [194, 187], "low_time": ["12:42", "--:--"], "low_tide": [122, "--"], "sunrise": "22:02", "sunset": "09:09", "tidetype": "長潮", "date": "02/19"}, "2020/02/20": {"tide": [49, 43, 52, 76, 110, 148, 182, 204, 211, 201, 177, 147, 121, 107, 107, 121, 146, 174, 195, 202, 193, 168, 130, 88], "high_time": ["07:54", "18:58"], "high_tide": [211, 202], "low_time": ["00:54", "13:31"], "low_tide": [43, 105], "sunrise": "22:01", "sunset": "09:10", "tidetype": "若潮", "date": "02/20"}, "2020/02/21": {"tide": [52, 31, 29, 45, 79, 123, 167, 203, 222, 222, 201, 165, 128, 99, 88, 95, 120, 156, 190, 213, 217, 201, 166, 118], "high_time": ["08:29", "19:43"], "high_tide": [224, 218], "low_time": ["01:38", "14:07"], "low_tide": [28, 88], "sunrise": "22:00", "sunset": "09:11", "tidetype": "中潮", "date": "02/21"}, "2020/02/22": {"tide": [69, 33, 16, 22, 50, 95, 146, 192, 223, 234, 222, 188, 143, 102, 77, 74, 93, 130, 174, 211, 229, 225, 199, 153], "high_time": ["08:59", "20:20"], "high_tide": [234, 230], "low_time": ["02:15", "14:38"], "low_tide": [16, 73], "sunrise": "21:58", "sunset": "09:11", "tidetype": "中潮", "date": "02/22"}, "2020/02/23": {"tide": [97, 47, 15, 8, 26, 67, 121, 175, 217, 238, 236, 209, 164, 114, 76, 61, 70, 102, 150, 197, 229, 239, 225, 186], "high_time": ["09:26", "20:54"], "high_tide": [241, 239], "low_time": ["02:47", "15:08"], "low_tide": [8, 60], "sunrise": "21:57", "sunset": "09:12", "tidetype": "大潮", "date": "02/23"}, "2020/02/24": {"tide": [131, 72, 27, 6, 12, 44, 95, 153, 203, 235, 243, 226, 185, 132, 84, 56, 54, 77, 121, 174, 218, 241, 240, 213], "high_time": ["09:50", "21:26"], "high_tide": [243, 244], "low_time": ["03:16", "15:36"], "low_tide": [5, 51], "sunrise": "21:56", "sunset": "09:13", "tidetype": "大潮", "date": "02/24"}, "2020/02/25": {"tide": [164, 103, 48, 14, 7, 28, 73, 130, 186, 225, 243, 235, 203, 152, 99, 60, 46, 58, 94, 146, 197, 232, 244, 230], "high_time": ["10:12", "21:57"], "high_tide": [243, 244], "low_time": ["03:44", "16:03"], "low_tide": [6, 46], "sunrise": "21:55", "sunset": "09:14", "tidetype": "大潮", "date": "02/25"}, "2020/02/26": {"tide": [191, 136, 77, 33, 13, 22, 57, 109, 166, 212, 237, 238, 215, 171, 118, 72, 46, 46, 72, 117, 169, 213, 237, 236], "high_time": ["10:33", "22:28"], "high_tide": [241, 239], "low_time": ["04:11", "16:30"], "low_tide": [13, 43], "sunrise": "21:54", "sunset": "09:15", "tidetype": "大潮", "date": "02/26"}, "2020/02/27": {"tide": [210, 164, 109, 59, 29, 26, 49, 93, 146, 195, 226, 236, 221, 186, 137, 89, 54, 43, 57, 92, 140, 187, 219, 231], "high_time": ["10:53", "22:59"], "high_tide": [236, 231], "low_time": ["04:37", "16:57"], "low_tide": [24, 43], "sunrise": "21:53", "sunset": "09:16", "tidetype": "中潮", "date": "02/27"}, "2020/02/28": {"tide": [219, 186, 138, 89, 52, 39, 50, 83, 129, 177, 212, 228, 222, 196, 155, 108, 69, 48, 50, 74, 113, 157, 194, 215], "high_time": ["11:14", "23:32"], "high_tide": [229, 218], "low_time": ["05:03", "17:25"], "low_tide": [39, 46], "sunrise": "21:52", "sunset": "09:17", "tidetype": "中潮", "date": "02/28"}, "2020/02/29": {"tide": [216, 197, 161, 119, 81, 59, 59, 80, 117, 159, 195, 216, 218, 201, 169, 128, 89, 61, 52, 63, 91, 128, 165, 192], "high_time": ["11:36", "--:--"], "high_tide": [220, "--"], "low_time": ["05:30", "17:57"], "low_tide": [56, 52], "sunrise": "21:50", "sunset": "09:17", "tidetype": "中潮", "date": "02/29"}}}