{"point": "QE", "name": "厳原", "lat": 34.2, "lon": 129.3, "data": {"2021/12/01": {"tide": [34, 40, 56, 80, 105, 128, 142, 142, 128, 103, 74, 50, 37, 39, 54, 79, 107, 133, 149, 151, 136, 108, 73, 42], "high_time": ["06:31", "18:36"], "high_tide": [143, 152], "low_time": ["00:00", "12:22"], "low_tide": [34, 36], "sunrise": "22:09", "sunset": "08:13", "tidetype": "若潮", "date": "12/01"}, "2021/12/02": {"tide": [22, 18, 29, 53, 84, 116, 143, 157, 155, 135, 103, 68, 40, 28, 34, 55, 85, 118, 146, 160, 157, 135, 99, 58], "high_time": ["07:22", "19:19"], "high_tide": [158, 161], "low_time": ["00:44", "13:10"], "low_tide": [17, 28], "sunrise": "22:10", "sunset": "08:13", "tidetype": "中潮", "date": "12/02"}, "2021/12/03": {"tide": [24, 5, 5, 23, 54, 91, 128, 157, 170, 164, 138, 100, 60, 32, 23, 33, 60, 95, 130, 157, 168, 159, 129, 87], "high_time": ["08:10", "20:03"], "high_tide": [171, 168], "low_time": ["01:28", "13:57"], "low_tide": [3, 23], "sunrise": "22:11", "sunset": "08:13", "tidetype": "中潮", "date": "12/03"}, "2021/12/04": {"tide": [43, 8, -7, -1, 23, 59, 100, 140, 168, 179, 167, 136, 93, 53, 27, 22, 37, 68, 105, 141, 165, 171, 155, 120], "high_time": ["08:59", "20:46"], "high_tide": [179, 171], "low_time": ["02:13", "14:43"], "low_tide": [-7, 21], "sunrise": "22:12", "sunset": "08:13", "tidetype": "大潮", "date": "12/04"}, "2021/12/05": {"tide": [74, 30, -2, -12, -1, 27, 66, 109, 148, 175, 181, 164, 129, 85, 47, 25, 26, 45, 78, 115, 148, 167, 167, 146], "high_time": ["09:46", "21:30"], "high_tide": [181, 170], "low_time": ["02:58", "15:29"], "low_tide": [-12, 23], "sunrise": "22:13", "sunset": "08:13", "tidetype": "大潮", "date": "12/05"}, "2021/12/06": {"tide": [109, 63, 22, -5, -10, 5, 35, 75, 117, 153, 175, 176, 156, 120, 78, 44, 28, 33, 55, 88, 122, 150, 163, 158], "high_time": ["10:34", "22:15"], "high_tide": [178, 164], "low_time": ["03:45", "16:15"], "low_tide": [-11, 28], "sunrise": "22:14", "sunset": "08:13", "tidetype": "大潮", "date": "12/06"}, "2021/12/07": {"tide": [135, 97, 55, 19, -1, -1, 16, 46, 84, 122, 152, 169, 166, 144, 109, 73, 45, 35, 43, 66, 95, 124, 145, 154], "high_time": ["11:22", "23:01"], "high_tide": [170, 154], "low_time": ["04:31", "17:01"], "low_tide": [-4, 35], "sunrise": "22:14", "sunset": "08:13", "tidetype": "大潮", "date": "12/07"}, "2021/12/08": {"tide": [146, 122, 88, 52, 23, 9, 12, 30, 58, 91, 123, 147, 158, 152, 131, 101, 70, 49, 44, 54, 73, 98, 121, 136], "high_time": ["12:10", "23:51"], "high_tide": [158, 141], "low_time": ["05:19", "17:50"], "low_tide": [8, 44], "sunrise": "22:15", "sunset": "08:13", "tidetype": "中潮", "date": "12/08"}, "2021/12/09": {"tide": [141, 132, 112, 83, 53, 31, 22, 27, 44, 68, 95, 120, 138, 145, 138, 120, 95, 71, 56, 53, 61, 77, 96, 113], "high_time": ["13:02", "--:--"], "high_tide": [145, "--"], "low_time": ["06:07", "18:44"], "low_tide": [22, 52], "sunrise": "22:16", "sunset": "08:13", "tidetype": "中潮", "date": "12/09"}, "2021/12/10": {"tide": [125, 128, 121, 104, 81, 58, 42, 36, 41, 55, 74, 95, 114, 128, 132, 127, 112, 92, 74, 61, 58, 64, 75, 89], "high_time": ["00:49", "13:59"], "high_tide": [128, 132], "low_time": ["07:00", "19:49"], "low_tide": [36, 58], "sunrise": "22:17", "sunset": "08:13", "tidetype": "中潮", "date": "12/10"}, "2021/12/11": {"tide": [103, 114, 117, 113, 101, 84, 66, 53, 49, 52, 63, 77, 93, 108, 119, 124, 120, 109, 92, 76, 64, 59, 61, 69], "high_time": ["02:00", "15:05"], "high_tide": [117, 124], "low_time": ["08:00", "21:10"], "low_tide": [49, 59], "sunrise": "22:18", "sunset": "08:13", "tidetype": "中潮", "date": "12/11"}, "2021/12/12": {"tide": [81, 94, 105, 112, 111, 102, 88, 74, 62, 57, 59, 66, 77, 90, 103, 114, 119, 118, 108, 93, 76, 62, 55, 55], "high_time": ["03:23", "16:16"], "high_tide": [112, 120], "low_time": ["09:14", "22:30"], "low_tide": [57, 54], "sunrise": "22:18", "sunset": "08:13", "tidetype": "小潮", "date": "12/12"}, "2021/12/13": {"tide": [62, 74, 89, 102, 111, 113, 107, 94, 80, 67, 60, 60, 65, 75, 88, 102, 114, 120, 118, 108, 91, 72, 55, 46], "high_time": ["04:43", "17:18"], "high_tide": [113, 120], "low_time": ["10:34", "23:31"], "low_tide": [59, 45], "sunrise": "22:19", "sunset": "08:14", "tidetype": "小潮", "date": "12/13"}, "2021/12/14": {"tide": [46, 55, 70, 88, 104, 116, 118, 112, 99, 82, 68, 59, 58, 63, 75, 89, 105, 117, 123, 119, 106, 85, 63, 45], "high_time": ["05:49", "18:08"], "high_tide": [119, 123], "low_time": ["11:41", "--:--"], "low_tide": [57, "--"], "sunrise": "22:20", "sunset": "08:14", "tidetype": "小潮", "date": "12/14"}, "2021/12/15": {"tide": [36, 38, 51, 70, 92, 111, 124, 126, 117, 101, 81, 64, 54, 54, 62, 77, 95, 112, 124, 127, 119, 101, 76, 51], "high_time": ["06:42", "18:49"], "high_tide": [126, 127], "low_time": ["00:18", "12:32"], "low_tide": [36, 53], "sunrise": "22:20", "sunset": "08:14", "tidetype": "長潮", "date": "12/15"}, "2021/12/16": {"tide": [33, 27, 34, 51, 76, 101, 122, 133, 132, 119, 98, 75, 56, 48, 51, 64, 82, 103, 121, 131, 129, 116, 92, 63], "high_time": ["07:26", "19:24"], "high_tide": [134, 132], "low_time": ["00:58", "13:14"], "low_tide": [27, 48], "sunrise": "22:21", "sunset": "08:15", "tidetype": "若潮", "date": "12/16"}, "2021/12/17": {"tide": [38, 22, 21, 33, 57, 85, 113, 134, 142, 136, 117, 91, 65, 48, 43, 51, 69, 92, 114, 130, 136, 128, 108, 79], "high_time": ["08:05", "19:56"], "high_tide": [142, 136], "low_time": ["01:36", "13:51"], "low_tide": [20, 43], "sunrise": "22:22", "sunset": "08:15", "tidetype": "中潮", "date": "12/17"}, "2021/12/18": {"tide": [48, 25, 14, 19, 38, 67, 98, 126, 144, 147, 135, 110, 80, 55, 41, 42, 56, 79, 104, 126, 138, 137, 122, 96], "high_time": ["08:41", "20:26"], "high_tide": [148, 139], "low_time": ["02:11", "14:26"], "low_tide": [14, 39], "sunrise": "22:22", "sunset": "08:15", "tidetype": "中潮", "date": "12/18"}, "2021/12/19": {"tide": [64, 34, 15, 11, 22, 47, 80, 113, 139, 152, 148, 128, 98, 67, 45, 37, 44, 65, 91, 117, 135, 141, 133, 112], "high_time": ["09:16", "20:56"], "high_tide": [152, 141], "low_time": ["02:45", "15:00"], "low_tide": [10, 37], "sunrise": "22:23", "sunset": "08:16", "tidetype": "大潮", "date": "12/19"}, "2021/12/20": {"tide": [81, 48, 22, 9, 12, 31, 60, 95, 127, 148, 154, 142, 116, 84, 55, 38, 37, 52, 76, 104, 127, 140, 140, 125], "high_time": ["09:50", "21:27"], "high_tide": [154, 142], "low_time": ["03:19", "15:32"], "low_tide": [8, 35], "sunrise": "22:23", "sunset": "08:16", "tidetype": "大潮", "date": "12/20"}, "2021/12/21": {"tide": [98, 66, 35, 14, 9, 19, 43, 75, 109, 137, 152, 150, 132, 102, 70, 45, 36, 42, 62, 89, 115, 134, 140, 133], "high_time": ["10:23", "21:59"], "high_tide": [153, 140], "low_time": ["03:52", "16:05"], "low_tide": [8, 36], "sunrise": "22:24", "sunset": "08:17", "tidetype": "大潮", "date": "12/21"}, "2021/12/22": {"tide": [113, 84, 52, 26, 12, 13, 30, 57, 90, 121, 143, 150, 141, 118, 87, 58, 41, 38, 51, 74, 99, 121, 135, 135], "high_time": ["10:57", "22:33"], "high_tide": [150, 136], "low_time": ["04:24", "16:38"], "low_tide": [10, 37], "sunrise": "22:24", "sunset": "08:17", "tidetype": "大潮", "date": "12/22"}, "2021/12/23": {"tide": [123, 99, 70, 42, 21, 14, 22, 43, 71, 102, 128, 143, 144, 129, 104, 75, 51, 41, 45, 61, 83, 106, 123, 130], "high_time": ["11:31", "23:10"], "high_tide": [145, 130], "low_time": ["04:58", "17:13"], "low_tide": [14, 40], "sunrise": "22:25", "sunset": "08:18", "tidetype": "中潮", "date": "12/23"}, "2021/12/24": {"tide": [126, 111, 87, 60, 36, 22, 21, 33, 56, 83, 110, 130, 139, 134, 117, 92, 67, 49, 44, 52, 68, 89, 107, 119], "high_time": ["12:09", "23:52"], "high_tide": [139, 123], "low_time": ["05:34", "17:52"], "low_tide": [20, 44], "sunrise": "22:25", "sunset": "08:18", "tidetype": "中潮", "date": "12/24"}, "2021/12/25": {"tide": [123, 117, 101, 79, 55, 36, 27, 30, 44, 66, 91, 113, 128, 132, 124, 107, 84, 63, 50, 48, 57, 72, 89, 103], "high_time": ["12:50", "--:--"], "high_tide": [132, "--"], "low_time": ["06:15", "18:38"], "low_tide": [27, 47], "sunrise": "22:26", "sunset": "08:19", "tidetype": "中潮", "date": "12/25"}, "2021/12/26": {"tide": [113, 115, 109, 95, 76, 56, 40, 34, 39, 53, 73, 94, 112, 124, 125, 117, 100, 80, 62, 51, 50, 57, 70, 84], "high_time": ["00:46", "13:40"], "high_tide": [115, 126], "low_time": ["07:03", "19:36"], "low_tide": [34, 49], "sunrise": "22:26", "sunset": "08:19", "tidetype": "中潮", "date": "12/26"}, "2021/12/27": {"tide": [97, 106, 110, 106, 95, 78, 61, 47, 41, 46, 58, 75, 94, 110, 120, 121, 114, 98, 79, 61, 50, 47, 53, 64], "high_time": ["01:58", "14:40"], "high_tide": [110, 122], "low_time": ["08:04", "20:48"], "low_tide": [41, 47], "sunrise": "22:26", "sunset": "08:20", "tidetype": "小潮", "date": "12/27"}, "2021/12/28": {"tide": [77, 91, 102, 108, 108, 100, 85, 68, 54, 47, 48, 58, 74, 91, 107, 118, 121, 115, 100, 80, 60, 46, 40, 44], "high_time": ["03:26", "15:49"], "high_tide": [109, 121], "low_time": ["09:18", "22:06"], "low_tide": [46, 40], "sunrise": "22:27", "sunset": "08:21", "tidetype": "小潮", "date": "12/28"}, "2021/12/29": {"tide": [54, 69, 86, 101, 112, 115, 109, 95, 77, 60, 49, 47, 55, 70, 89, 107, 121, 125, 119, 103, 80, 56, 38, 29], "high_time": ["04:53", "16:56"], "high_tide": [115, 125], "low_time": ["10:38", "23:16"], "low_tide": [47, 29], "sunrise": "22:27", "sunset": "08:21", "tidetype": "小潮", "date": "12/29"}, "2021/12/30": {"tide": [32, 43, 61, 83, 104, 120, 127, 122, 107, 84, 62, 47, 43, 50, 67, 88, 110, 126, 132, 125, 106, 78, 49, 27], "high_time": ["06:06", "17:58"], "high_tide": [127, 132], "low_time": ["11:50", "--:--"], "low_tide": [43, "--"], "sunrise": "22:27", "sunset": "08:22", "tidetype": "長潮", "date": "12/30"}, "2021/12/31": {"tide": [17, 20, 34, 56, 83, 110, 131, 140, 135, 116, 89, 62, 43, 37, 46, 65, 90, 116, 134, 140, 130, 107, 74, 40], "high_time": ["07:10", "18:54"], "high_tide": [140, 140], "low_time": ["00:16", "12:53"], "low_tide": [16, 37], "sunrise": "22:28", "sunset": "08:23", "tidetype": "若潮", "date": "12/31"}}}