{"point": "CF", "name": "長府", "lat": 34.01666667, "lon": 131.0, "data": {"2020/06/01": {"tide": [141, 185, 237, 284, 316, 326, 312, 278, 231, 183, 142, 118, 119, 145, 189, 238, 279, 303, 302, 278, 236, 188, 145, 115], "high_time": ["04:56", "17:30"], "high_tide": [326, 306], "low_time": ["11:28", "23:41"], "low_tide": [115, 109], "sunrise": "20:05", "sunset": "10:22", "tidetype": "小潮", "date": "06/01"}, "2020/06/02": {"tide": [110, 134, 182, 238, 290, 325, 336, 318, 274, 218, 160, 111, 83, 87, 125, 183, 245, 298, 331, 333, 304, 255, 200, 149], "high_time": ["05:53", "18:34"], "high_tide": [337, 336], "low_time": ["12:23", "--:--"], "low_tide": [81, "--"], "sunrise": "20:05", "sunset": "10:23", "tidetype": "長潮", "date": "06/02"}, "2020/06/03": {"tide": [112, 104, 132, 186, 248, 303, 339, 345, 317, 262, 195, 130, 76, 49, 63, 115, 187, 261, 323, 359, 358, 322, 266, 204], "high_time": ["06:42", "19:29"], "high_tide": [347, 364], "low_time": ["00:44", "13:11"], "low_tide": [103, 48], "sunrise": "20:05", "sunset": "10:23", "tidetype": "若潮", "date": "06/03"}, "2020/06/04": {"tide": [147, 107, 103, 139, 199, 264, 319, 351, 348, 307, 240, 166, 96, 42, 22, 50, 117, 201, 282, 348, 382, 373, 329, 267], "high_time": ["07:26", "20:18"], "high_tide": [355, 384], "low_time": ["01:37", "13:56"], "low_tide": [100, 22], "sunrise": "20:04", "sunset": "10:24", "tidetype": "中潮", "date": "06/04"}, "2020/06/05": {"tide": [201, 141, 104, 109, 154, 219, 283, 334, 358, 342, 288, 214, 136, 65, 16, 8, 52, 131, 220, 304, 368, 394, 376, 325], "high_time": ["08:08", "21:05"], "high_tide": [358, 394], "low_time": ["02:24", "14:39"], "low_tide": [100, 5], "sunrise": "20:04", "sunset": "10:24", "tidetype": "中潮", "date": "06/05"}, "2020/06/06": {"tide": [260, 193, 135, 106, 122, 175, 241, 301, 344, 356, 326, 263, 186, 108, 41, 2, 10, 67, 152, 243, 324, 380, 394, 367], "high_time": ["08:48", "21:49"], "high_tide": [357, 395], "low_time": ["03:09", "15:21"], "low_tide": [106, -1], "sunrise": "20:04", "sunset": "10:25", "tidetype": "大潮", "date": "06/06"}, "2020/06/07": {"tide": [312, 247, 182, 132, 115, 142, 199, 261, 314, 347, 345, 304, 236, 160, 87, 28, 3, 26, 91, 178, 264, 337, 381, 384], "high_time": ["09:28", "22:33"], "high_tide": [351, 388], "low_time": ["03:53", "16:03"], "low_tide": [115, 3], "sunrise": "20:04", "sunset": "10:25", "tidetype": "大潮", "date": "06/07"}, "2020/06/08": {"tide": [349, 293, 231, 172, 133, 129, 164, 220, 276, 320, 341, 327, 279, 211, 140, 74, 27, 17, 52, 121, 204, 282, 343, 373], "high_time": ["10:08", "23:17"], "high_tide": [341, 375], "low_time": ["04:35", "16:44"], "low_tide": [125, 15], "sunrise": "20:04", "sunset": "10:26", "tidetype": "大潮", "date": "06/08"}, "2020/06/09": {"tide": [365, 326, 273, 216, 166, 139, 146, 185, 237, 284, 318, 327, 304, 254, 190, 126, 71, 39, 43, 85, 153, 227, 294, 341], "high_time": ["10:48", "--:--"], "high_tide": [327, "--"], "low_time": ["05:17", "17:25"], "low_tide": [137, 35], "sunrise": "20:04", "sunset": "10:26", "tidetype": "大潮", "date": "06/09"}, "2020/06/10": {"tide": [358, 343, 303, 253, 203, 164, 148, 163, 201, 246, 284, 307, 308, 281, 232, 176, 121, 79, 60, 75, 119, 181, 245, 299], "high_time": ["00:00", "11:31"], "high_tide": [358, 311], "low_time": ["06:00", "18:05"], "low_tide": [148, 60], "sunrise": "20:03", "sunset": "10:27", "tidetype": "中潮", "date": "06/10"}, "2020/06/11": {"tide": [333, 340, 320, 282, 237, 195, 166, 159, 176, 210, 246, 276, 292, 287, 260, 217, 169, 126, 96, 88, 108, 150, 203, 255], "high_time": ["00:44", "12:17"], "high_tide": [341, 293], "low_time": ["06:47", "18:47"], "low_tide": [158, 87], "sunrise": "20:03", "sunset": "10:27", "tidetype": "中潮", "date": "06/11"}, "2020/06/12": {"tide": [297, 320, 321, 300, 266, 227, 192, 170, 167, 182, 209, 239, 263, 275, 270, 246, 211, 173, 139, 119, 117, 137, 172, 216], "high_time": ["01:31", "13:12"], "high_tide": [323, 276], "low_time": ["07:40", "19:35"], "low_tide": [165, 115], "sunrise": "20:03", "sunset": "10:28", "tidetype": "中潮", "date": "06/12"}, "2020/06/13": {"tide": [258, 290, 307, 305, 286, 256, 222, 191, 172, 168, 179, 201, 227, 250, 262, 260, 243, 215, 185, 158, 143, 142, 157, 185], "high_time": ["02:23", "14:21"], "high_tide": [308, 263], "low_time": ["08:45", "20:33"], "low_tide": [167, 140], "sunrise": "20:03", "sunset": "10:28", "tidetype": "中潮", "date": "06/13"}, "2020/06/14": {"tide": [221, 256, 283, 297, 295, 278, 251, 218, 188, 167, 160, 167, 187, 214, 240, 256, 260, 250, 229, 203, 179, 162, 158, 167], "high_time": ["03:23", "15:46"], "high_tide": [298, 260], "low_time": ["10:00", "21:50"], "low_tide": [160, 158], "sunrise": "20:03", "sunset": "10:28", "tidetype": "小潮", "date": "06/14"}, "2020/06/15": {"tide": [190, 221, 253, 279, 293, 292, 276, 247, 212, 179, 154, 143, 150, 174, 206, 238, 261, 271, 266, 247, 221, 194, 173, 163], "high_time": ["04:27", "17:09"], "high_tide": [295, 272], "low_time": ["11:06", "23:11"], "low_tide": [143, 163], "sunrise": "20:03", "sunset": "10:29", "tidetype": "小潮", "date": "06/15"}, "2020/06/16": {"tide": [169, 189, 221, 254, 281, 296, 294, 274, 240, 199, 160, 132, 121, 133, 165, 207, 247, 278, 292, 286, 264, 233, 201, 174], "high_time": ["05:25", "18:13"], "high_tide": [297, 292], "low_time": ["11:58", "--:--"], "low_tide": [121, "--"], "sunrise": "20:04", "sunset": "10:29", "tidetype": "小潮", "date": "06/16"}, "2020/06/17": {"tide": [160, 166, 189, 224, 261, 289, 303, 296, 269, 226, 178, 134, 104, 99, 122, 166, 218, 267, 302, 315, 305, 275, 237, 197], "high_time": ["06:12", "19:03"], "high_tide": [304, 315], "low_time": ["00:14", "12:41"], "low_tide": [160, 98], "sunrise": "20:04", "sunset": "10:29", "tidetype": "長潮", "date": "06/17"}, "2020/06/18": {"tide": [166, 153, 163, 195, 235, 275, 303, 311, 295, 256, 204, 149, 103, 77, 83, 121, 178, 241, 295, 329, 336, 316, 277, 230], "high_time": ["06:52", "19:44"], "high_tide": [312, 337], "low_time": ["01:04", "13:19"], "low_tide": [153, 75], "sunrise": "20:04", "sunset": "10:30", "tidetype": "若潮", "date": "06/18"}, "2020/06/19": {"tide": [185, 153, 146, 167, 207, 253, 293, 317, 316, 286, 235, 175, 116, 71, 56, 78, 132, 201, 270, 324, 353, 349, 316, 268], "high_time": ["07:27", "20:22"], "high_tide": [320, 355], "low_time": ["01:45", "13:55"], "low_tide": [145, 56], "sunrise": "20:04", "sunset": "10:30", "tidetype": "中潮", "date": "06/19"}, "2020/06/20": {"tide": [215, 168, 141, 145, 178, 227, 275, 312, 328, 313, 269, 208, 143, 83, 45, 44, 84, 152, 230, 301, 351, 369, 351, 307], "high_time": ["08:02", "20:58"], "high_tide": [328, 369], "low_time": ["02:23", "14:32"], "low_tide": [139, 40], "sunrise": "20:04", "sunset": "10:30", "tidetype": "中潮", "date": "06/20"}, "2020/06/21": {"tide": [252, 196, 152, 134, 152, 197, 250, 297, 328, 331, 301, 245, 178, 111, 55, 28, 44, 101, 180, 261, 329, 370, 374, 343], "high_time": ["08:36", "21:36"], "high_tide": [334, 377], "low_time": ["03:00", "15:09"], "low_tide": [134, 28], "sunrise": "20:04", "sunset": "10:30", "tidetype": "大潮", "date": "06/21"}, "2020/06/22": {"tide": [291, 232, 177, 139, 135, 166, 219, 273, 316, 337, 327, 283, 219, 149, 83, 35, 22, 56, 125, 209, 289, 350, 380, 370], "high_time": ["09:12", "22:15"], "high_tide": [338, 381], "low_time": ["03:38", "15:48"], "low_tide": [132, 21], "sunrise": "20:05", "sunset": "10:30", "tidetype": "大潮", "date": "06/22"}, "2020/06/23": {"tide": [328, 271, 213, 161, 133, 142, 184, 240, 292, 327, 338, 315, 262, 194, 124, 64, 26, 28, 76, 153, 237, 312, 364, 380], "high_time": ["09:51", "22:55"], "high_tide": [339, 380], "low_time": ["04:17", "16:28"], "low_tide": [132, 21], "sunrise": "20:05", "sunset": "10:31", "tidetype": "大潮", "date": "06/23"}, "2020/06/24": {"tide": [358, 310, 252, 196, 151, 134, 154, 202, 257, 303, 331, 332, 300, 241, 173, 107, 54, 27, 43, 101, 181, 260, 327, 368], "high_time": ["10:32", "23:38"], "high_tide": [336, 376], "low_time": ["04:58", "17:09"], "low_tide": [134, 26], "sunrise": "20:05", "sunset": "10:31", "tidetype": "大潮", "date": "06/24"}, "2020/06/25": {"tide": [373, 342, 291, 235, 183, 145, 138, 166, 216, 267, 307, 328, 322, 284, 225, 160, 100, 55, 39, 66, 128, 204, 277, 334], "high_time": ["11:18", "--:--"], "high_tide": [329, "--"], "low_time": ["05:42", "17:53"], "low_tide": [136, 39], "sunrise": "20:05", "sunset": "10:31", "tidetype": "中潮", "date": "06/25"}, "2020/06/26": {"tide": [365, 360, 325, 275, 221, 174, 144, 144, 175, 221, 267, 302, 319, 309, 271, 216, 157, 104, 67, 60, 92, 152, 221, 285], "high_time": ["00:22", "12:10"], "high_tide": [367, 320], "low_time": ["06:30", "18:40"], "low_tide": [139, 58], "sunrise": "20:06", "sunset": "10:31", "tidetype": "中潮", "date": "06/26"}, "2020/06/27": {"tide": [334, 356, 346, 309, 261, 211, 168, 143, 146, 175, 217, 259, 292, 308, 299, 265, 216, 165, 118, 88, 87, 117, 171, 231], "high_time": ["01:10", "13:10"], "high_tide": [357, 309], "low_time": ["07:24", "19:33"], "low_tide": [140, 83], "sunrise": "20:06", "sunset": "10:31", "tidetype": "中潮", "date": "06/27"}, "2020/06/28": {"tide": [287, 328, 344, 332, 297, 252, 204, 163, 140, 142, 167, 205, 246, 280, 299, 295, 268, 228, 183, 141, 115, 113, 137, 182], "high_time": ["02:03", "14:19"], "high_tide": [344, 300], "low_time": ["08:26", "20:35"], "low_tide": [137, 110], "sunrise": "20:06", "sunset": "10:31", "tidetype": "中潮", "date": "06/28"}, "2020/06/29": {"tide": [235, 284, 320, 333, 321, 289, 245, 198, 157, 131, 129, 150, 187, 230, 269, 295, 299, 281, 248, 207, 168, 141, 133, 150], "high_time": ["03:00", "15:41"], "high_tide": [333, 300], "low_time": ["09:36", "21:49"], "low_tide": [127, 133], "sunrise": "20:07", "sunset": "10:31", "tidetype": "小潮", "date": "06/29"}, "2020/06/30": {"tide": [187, 234, 279, 313, 326, 316, 284, 240, 191, 146, 116, 109, 128, 167, 216, 264, 298, 312, 302, 273, 234, 193, 161, 146], "high_time": ["04:04", "17:05"], "high_tide": [326, 312], "low_time": ["10:47", "23:08"], "low_tide": [108, 146], "sunrise": "20:07", "sunset": "10:31", "tidetype": "小潮", "date": "06/30"}}}